usefulenums/__init__.py
usefulenums/enum.py
usefulenums/test_enum.py
django_useful_enums-1.0.1.dist-info/LICENSE.txt
django_useful_enums-1.0.1.dist-info/METADATA
django_useful_enums-1.0.1.dist-info/WHEEL
django_useful_enums-1.0.1.dist-info/top_level.txt
django_useful_enums-1.0.1.dist-info/RECORD
