Metadata-Version: 2.1
Name: django-useful-enums
Version: 1.0.1
Summary: A useful enumeration / choice library for Django.
Home-page: https://github.com/grahambinns/django-useful-enums
Author: Graham Binns
Author-email: graham@outcoded.dev
License: UNKNOWN
Download-URL: https://github.com/grahambinns/django-useful-enums/archive/1.0.tar.gz
Keywords: django,choices,enumerations
Platform: UNKNOWN
Classifier: Programming Language :: Python :: 3
Classifier: License :: OSI Approved :: MIT License
Classifier: Operating System :: OS Independent
Requires-Dist: stringcase
